{
	"configurations" : 
	[
		{
			"directories" : 
			[
				{
					"build" : ".",
					"childIndexes" : 
					[
						1
					],
					"jsonFile" : "directory-.-Debug-d0094a50bb2071803777.json",
					"minimumCMakeVersion" : 
					{
						"string" : "3.29.0"
					},
					"projectIndex" : 0,
					"source" : "."
				},
				{
					"build" : "src",
					"childIndexes" : 
					[
						2,
						3
					],
					"jsonFile" : "directory-src-Debug-c94b7c2814d5a21df52c.json",
					"minimumCMakeVersion" : 
					{
						"string" : "3.29.0"
					},
					"parentIndex" : 0,
					"projectIndex" : 1,
					"source" : "src",
					"targetIndexes" : 
					[
						0
					]
				},
				{
					"build" : "src/process",
					"jsonFile" : "directory-src.process-Debug-f5b9ab86de4ccee3c7f9.json",
					"minimumCMakeVersion" : 
					{
						"string" : "3.29.0"
					},
					"parentIndex" : 1,
					"projectIndex" : 2,
					"source" : "src/process",
					"targetIndexes" : 
					[
						2
					]
				},
				{
					"build" : "src/pm_map",
					"jsonFile" : "directory-src.pm_map-Debug-2e6b10867b5cf0516f06.json",
					"minimumCMakeVersion" : 
					{
						"string" : "3.29.0"
					},
					"parentIndex" : 1,
					"projectIndex" : 3,
					"source" : "src/pm_map",
					"targetIndexes" : 
					[
						1
					]
				}
			],
			"name" : "Debug",
			"projects" : 
			[
				{
					"childIndexes" : 
					[
						1
					],
					"directoryIndexes" : 
					[
						0
					],
					"name" : "planning"
				},
				{
					"childIndexes" : 
					[
						2,
						3
					],
					"directoryIndexes" : 
					[
						1
					],
					"name" : "main",
					"parentIndex" : 0,
					"targetIndexes" : 
					[
						0
					]
				},
				{
					"directoryIndexes" : 
					[
						2
					],
					"name" : "process",
					"parentIndex" : 1,
					"targetIndexes" : 
					[
						2
					]
				},
				{
					"directoryIndexes" : 
					[
						3
					],
					"name" : "pm_map",
					"parentIndex" : 1,
					"targetIndexes" : 
					[
						1
					]
				}
			],
			"targets" : 
			[
				{
					"directoryIndex" : 1,
					"id" : "main::@145eef247bfb46b6828c",
					"jsonFile" : "target-main-Debug-495f59600ded6673dc28.json",
					"name" : "main",
					"projectIndex" : 1
				},
				{
					"directoryIndex" : 3,
					"id" : "pm_map::@3b326c392eeb5136fd6a",
					"jsonFile" : "target-pm_map-Debug-4ae8a45afdd49acca7eb.json",
					"name" : "pm_map",
					"projectIndex" : 3
				},
				{
					"directoryIndex" : 2,
					"id" : "process::@0c136a57587ef2cf0836",
					"jsonFile" : "target-process-Debug-712822e56779655751e7.json",
					"name" : "process",
					"projectIndex" : 2
				}
			]
		}
	],
	"kind" : "codemodel",
	"paths" : 
	{
		"build" : "E:/NEU/Cmake_planning_test/build",
		"source" : "E:/NEU/Cmake_planning_test"
	},
	"version" : 
	{
		"major" : 2,
		"minor" : 8
	}
}
